react_router_routes/__init__.py
react_router_routes/generate.py
react_router_routes-0.2.1.dist-info/WHEEL
react_router_routes-0.2.1.dist-info/entry_points.txt
react_router_routes-0.2.1.dist-info/METADATA
react_router_routes-0.2.1.dist-info/RECORD
