Metadata-Version: 2.3
Name: react-router-routes
Version: 0.2.1
Summary: Generate strongly-typed Python helpers (TypedDict param classes + path/url builders) from a React Router v6+ route tree so Python code can build frontend URLs safely.
Keywords: react-router,router,routes,url-generation,typed-routes,typed,cli,backend,frontend,integration
Author: Michael Bianco
Author-email: Michael Bianco <mike@mikebian.co>
Requires-Dist: typer>=0.12.5
Requires-Dist: jinja2>=3.1.4
Requires-Python: >=3.11
Project-URL: Repository, https://github.com/iloveitaly/react-router-routes
